decawave_1001_rjg/__init__.py
decawave_1001_rjg/abstract_interrupt.py
decawave_1001_rjg/decawave_1001.py
decawave_1001_rjg/gpio_interrupt.py
decawave_1001_rjg/messages/__init__.py
decawave_1001_rjg/messages/dwm_config_response.py
decawave_1001_rjg/messages/dwm_distance_and_position.py
decawave_1001_rjg/messages/dwm_interrupt_config_request.py
decawave_1001_rjg/messages/dwm_location_response.py
decawave_1001_rjg/messages/dwm_position.py
decawave_1001_rjg/messages/dwm_position_response.py
decawave_1001_rjg/messages/dwm_request.py
decawave_1001_rjg/messages/dwm_response.py
decawave_1001_rjg/messages/dwm_status_response.py
decawave_1001_rjg/messages/dwm_version_response.py
decawave_1001_rjg/messages/simple_dwm_request.py
decawave_1001_rjg/messages/tlv_message.py
examples/__init__.py
examples/simple.py
test/__init__.py
test/messages_test/__init__.py
test/messages_test/test_dwm_config_response.py
test/messages_test/test_dwm_distance_and_position.py
test/messages_test/test_dwm_interrupt_config_request.py
test/messages_test/test_dwm_location_response.py
test/messages_test/test_dwm_position.py
test/messages_test/test_dwm_position_response.py
test/messages_test/test_dwm_response.py
test/messages_test/test_dwm_status_response.py
test/messages_test/test_dwm_version_response.py
test/messages_test/test_simple_dwm_request.py
test/messages_test/test_tlv_message.py
decawave_1001_rjg-1.0.dist-info/LICENSE.txt
decawave_1001_rjg-1.0.dist-info/METADATA
decawave_1001_rjg-1.0.dist-info/WHEEL
decawave_1001_rjg-1.0.dist-info/top_level.txt
decawave_1001_rjg-1.0.dist-info/RECORD
