Metadata-Version: 2.1
Name: decawave-1001-rjg
Version: 1.0
Summary: A python module to enable a Raspberry Pi to read the Decawave 1001 UWB positioning module.
Home-page: https://github.com/Richard-Gemmell/decawave-1001-rjg
Author: Richard Gemmell
Author-email: 16683467+Richard-Gemmell@users.noreply.github.com
License: LICENSE.txt
Platform: UNKNOWN
Classifier: Programming Language :: Python :: 3.7
Classifier: License :: OSI Approved :: MIT License
Classifier: Operating System :: OS Independent
Classifier: Topic :: Software Development :: Embedded Systems
Classifier: Topic :: System :: Hardware :: Hardware Drivers
Requires-Dist: spidev (>=3.2)
